kagent/core/__init__.py
kagent/core/_config.py
kagent/core/_logging.py
kagent/core/a2a/__init__.py
kagent/core/a2a/_consts.py
kagent/core/a2a/_hitl.py
kagent/core/a2a/_requests.py
kagent/core/a2a/_task_result_aggregator.py
kagent/core/a2a/_task_store.py
kagent/core/tracing/__init__.py
kagent/core/tracing/_span_processor.py
kagent/core/tracing/_utils.py
kagent_core-0.7.8.dist-info/METADATA
kagent_core-0.7.8.dist-info/WHEEL
kagent_core-0.7.8.dist-info/RECORD
