Metadata-Version: 2.4
Name: kagent-core
Version: 0.7.8
Summary: kagent common library for kagent python packages
Requires-Python: >=3.11.0
Requires-Dist: a2a-sdk[http-server]>=0.3.9
Requires-Dist: opentelemetry-api>=1.36.0
Requires-Dist: opentelemetry-exporter-otlp-proto-grpc>=1.36.0
Requires-Dist: opentelemetry-instrumentation-anthropic>=0.44.0
Requires-Dist: opentelemetry-instrumentation-fastapi>=0.52.0
Requires-Dist: opentelemetry-instrumentation-google-generativeai>=0.47.3
Requires-Dist: opentelemetry-instrumentation-httpx>=0.52.0
Requires-Dist: opentelemetry-instrumentation-openai>=0.44.3
Requires-Dist: opentelemetry-sdk>=1.36.0
